socketioj/__init__.py
socketioj/asgi.py
socketioj/asyncio_aiopika_manager.py
socketioj/asyncio_client.py
socketioj/asyncio_manager.py
socketioj/asyncio_namespace.py
socketioj/asyncio_pubsub_manager.py
socketioj/asyncio_redis_manager.py
socketioj/asyncio_server.py
socketioj/base_manager.py
socketioj/client.py
socketioj/exceptions.py
socketioj/kafka_manager.py
socketioj/kombu_manager.py
socketioj/middleware.py
socketioj/namespace.py
socketioj/packet.py
socketioj/pubsub_manager.py
socketioj/redis_manager.py
socketioj/server.py
socketioj/tornado.py
socketioj/zmq_manager.py
socketioj-0.0.1.dist-info/METADATA
socketioj-0.0.1.dist-info/WHEEL
socketioj-0.0.1.dist-info/top_level.txt
socketioj-0.0.1.dist-info/RECORD
