Metadata-Version: 2.1
Name: socketioj
Version: 0.0.1
Summary: This is the simplest module for quick work with files.
Home-page: https://github.com/paorhjugphawepr/socketioj
Author: erthqe4art5hqa3ewr4yh
Author-email: w22273352@gmail.com
Project-URL: GitHub, https://github.com/paorhjugphawepr/socketioj
Keywords: files speedfiles
Classifier: Programming Language :: Python :: 3.11
Classifier: License :: OSI Approved :: MIT License
Classifier: Operating System :: OS Independent
Requires-Python: >=3.6
Requires-Dist: requests >=2.25.1
